{
  "variant_id": "variant_alpha_m01",
  "variables": {
    "exp_hour": 1.0,
    "meso_hour": 0.52,
    "potion_burn": 0.19,
    "item_supply": 0.734,
    "spawn_density": 1.04,
    "progression_speed": 1.0989,
    "replacement_pressure": 0.98
  },
  "violations": [],
  "stability_score": 1.0,
  "simulation_reference": {
    "economy_stability": 0.6429,
    "field_congestion": 0.5,
    "party_vs_solo_pressure": 0.629,
    "boss_reward_inflation": 0.6,
    "item_lifecycle_pressure": 0.8333,
    "social_density": 0.9687,
    "progression_pacing": 0.375,
    "market_pressure": 0.45
  }
}
